btjenesten/__init__.py
btjenesten/analysis.py
btjenesten/bbtools.py
btjenesten/btjenesten.py
btjenesten/gpr.py
btjenesten/gpr_test.py
btjenesten/kernels.py
btjenesten-0.26.dist-info/METADATA
btjenesten-0.26.dist-info/WHEEL
btjenesten-0.26.dist-info/top_level.txt
btjenesten-0.26.dist-info/RECORD
