Metadata-Version: 2.1
Name: btjenesten
Version: 0.26
Summary: Tools for a brilliant future
Home-page: https://github.uio.no/audunsh/btjenesten
Author: Audun Skau Hansen
Author-email: a.s.hansen@kjemi.uio.no
License: UNKNOWN
Platform: UNKNOWN
Classifier: Programming Language :: Python :: 3
Classifier: License :: OSI Approved :: MIT License
Classifier: Operating System :: OS Independent
